cloudformation_loader/__init__.py
cloudformation_loader/odict.py
cloudformation_loader/yaml_loader.py
cloudformation_loader-0.1.0.dist-info/METADATA
cloudformation_loader-0.1.0.dist-info/WHEEL
cloudformation_loader-0.1.0.dist-info/top_level.txt
cloudformation_loader-0.1.0.dist-info/RECORD
