Metadata-Version: 2.4
Name: cloudformation-loader
Version: 0.1.0
Summary: Import Python code embedded in CloudFormation Templates without hassle. Helps you test your Lambda Functions
License-Expression: Apache-2.0
Project-URL: Homepage, https://github.com/pplu/cloudformation-loader
Project-URL: Documentation, https://github.com/pplu/cloudformation-loader
Project-URL: Repository, https://github.com/pplu/cloudformation-loader.git
Project-URL: Issues, https://github.com/pplu/cloudformation-loader/issues
Keywords: aws,lambda,test,cloudformation
Classifier: Development Status :: 4 - Beta
Classifier: Intended Audience :: Developers
Classifier: Topic :: Software Development :: Testing
Requires-Python: >=3.10
Requires-Dist: pyyaml>=6.0.2
